odoo8_addon_hr_employee_no_welcome-8.0.1.0.0.99.dev6-py2.7-nspkg.pth
odoo8_addon_hr_employee_no_welcome-8.0.1.0.0.99.dev6.dist-info/METADATA
odoo8_addon_hr_employee_no_welcome-8.0.1.0.0.99.dev6.dist-info/RECORD
odoo8_addon_hr_employee_no_welcome-8.0.1.0.0.99.dev6.dist-info/WHEEL
odoo8_addon_hr_employee_no_welcome-8.0.1.0.0.99.dev6.dist-info/namespace_packages.txt
odoo8_addon_hr_employee_no_welcome-8.0.1.0.0.99.dev6.dist-info/top_level.txt
odoo_addons/hr_employee_no_welcome/README.rst
odoo_addons/hr_employee_no_welcome/__init__.py
odoo_addons/hr_employee_no_welcome/__openerp__.py
odoo_addons/hr_employee_no_welcome/i18n/ar.po
odoo_addons/hr_employee_no_welcome/i18n/de.po
odoo_addons/hr_employee_no_welcome/i18n/es.po
odoo_addons/hr_employee_no_welcome/i18n/fi.po
odoo_addons/hr_employee_no_welcome/i18n/fr.po
odoo_addons/hr_employee_no_welcome/i18n/fr_CA.po
odoo_addons/hr_employee_no_welcome/i18n/hr_employee_no_welcome.pot
odoo_addons/hr_employee_no_welcome/i18n/it.po
odoo_addons/hr_employee_no_welcome/i18n/nb_NO.po
odoo_addons/hr_employee_no_welcome/i18n/nl.po
odoo_addons/hr_employee_no_welcome/i18n/nl_NL.po
odoo_addons/hr_employee_no_welcome/i18n/pt_BR.po
odoo_addons/hr_employee_no_welcome/i18n/ro.po
odoo_addons/hr_employee_no_welcome/i18n/sl.po
odoo_addons/hr_employee_no_welcome/i18n/tr.po
odoo_addons/hr_employee_no_welcome/models/__init__.py
odoo_addons/hr_employee_no_welcome/models/hr_employee.py
odoo_addons/hr_employee_no_welcome/static/description/icon.png
